[
    {
      "name": "Khan",
      "age": 23,
      "gender": "male",
      "location": "medical",
      "phoneNo": 8806255273
    },
    {
      "name": "ahmad",
      "age": 23,
      "gender": "male",
      "location": "medical",
      "phoneNo": 8806255273
    },
    {
      "name": "khalid",
      "age": 23,
      "gender": "male",
      "location": "medical",
      "phoneNo": 8806255273
    },
    {
      "name": "latif",
      "age": 23,
      "gender": "male",
      "location": "medical",
      "phoneNo": 8806255273
    },
    {
      "name": "ankit",
      "age": 23,
      "gender": "male",
      "location": "medical",
      "phoneNo": 8806255273
    }
  ]